pysnowball/__init__.py
pysnowball/api_ref.py
pysnowball/bond.py
pysnowball/capital.py
pysnowball/cons.py
pysnowball/cube.py
pysnowball/f10.py
pysnowball/finance.py
pysnowball/fund.py
pysnowball/hkex.py
pysnowball/index.py
pysnowball/realtime.py
pysnowball/report.py
pysnowball/suggest.py
pysnowball/token.py
pysnowball/user.py
pysnowball/utls.py
pysnowball-0.1.8.dist-info/licenses/LICENSE
tests/__init__.py
tests/test_fund.py
pysnowball-0.1.8.dist-info/METADATA
pysnowball-0.1.8.dist-info/WHEEL
pysnowball-0.1.8.dist-info/top_level.txt
pysnowball-0.1.8.dist-info/RECORD
