Metadata-Version: 2.4
Name: pysnowball
Version: 0.1.8
Summary: xueqiu api python client | 集成雪球API
Home-page: https://github.com/uname-yang/pysnowball
Author: Yang Yu
Author-email: yang.lights@hotmail.com
Keywords: Financial Data,XueQiu,Snow Ball,雪球,Python Api
Classifier: Programming Language :: Python :: 3
Classifier: License :: OSI Approved :: MIT License
Classifier: Operating System :: OS Independent
License-File: LICENSE
Requires-Dist: requests>=2.18.4
Requires-Dist: beautifulsoup4>=4.10.0
Dynamic: author
Dynamic: author-email
Dynamic: classifier
Dynamic: description
Dynamic: description-content-type
Dynamic: home-page
Dynamic: keywords
Dynamic: license-file
Dynamic: requires-dist
Dynamic: summary
